multimodal_communication/.python-version
multimodal_communication/__init__.py
multimodal_communication/gcloud_helper/__init__.py
multimodal_communication/gcloud_helper/cloud_functions.py
multimodal_communication/python_texting/__init__.py
multimodal_communication/python_texting/texting.py
multimodal_communication/s3_helper/delta_functions.py
multimodal_communication/s3_helper/s3_functions.py
multimodal_communication-0.4.4.dist-info/METADATA
multimodal_communication-0.4.4.dist-info/WHEEL
multimodal_communication-0.4.4.dist-info/entry_points.txt
multimodal_communication-0.4.4.dist-info/RECORD
