Metadata-Version: 2.4
Name: multimodal-communication
Version: 0.4.4
Summary: Add your description here
Requires-Python: >=3.10
Requires-Dist: aiosmtplib>=4.0.2
Requires-Dist: boto3>=1.40.6
Requires-Dist: build>=1.2.2.post1
Requires-Dist: deltalake>=1.1.4
Requires-Dist: fastparquet>=2024.11.0
Requires-Dist: google-cloud-storage>=3.1.0
Requires-Dist: google-cloud>=0.34.0
Requires-Dist: pandas>=2.2.3
Requires-Dist: polars>=1.31.0
Requires-Dist: pyarrow>=20.0.0
Requires-Dist: pytest>=8.4.2
Requires-Dist: python-dotenv>=1.1.1
Requires-Dist: ruff>=0.12.11
